{"cameraMode":{"drawMode":0,"name":"Shaded","section":"Shading Mode"},"sceneLighting":true,"audioPlay":false,"sceneViewState":{"showFog":true,"showMaterialUpdate":false,"showSkybox":true,"showFlares":true,"showImageEffects":true,"showParticleSystems":true},"in2DMode":false,"pivot":{"x":88.1635513305664,"y":0.9022648334503174,"z":6.298814296722412},"rotation":{"x":0.1003170907497406,"y":-0.8708919882774353,"z":0.20062215626239777,"w":0.43750104308128359},"size":4.421262264251709,"orthographic":false}